sdgym/__init__.py
sdgym/_dataset_utils.py
sdgym/benchmark.py
sdgym/dataset_explorer.py
sdgym/datasets.py
sdgym/errors.py
sdgym/metrics.py
sdgym/progress.py
sdgym/result_writer.py
sdgym/s3.py
sdgym/synthesizer_descriptions.yaml
sdgym/utils.py
sdgym/_benchmark/__init__.py
sdgym/_benchmark/benchmark.py
sdgym/_benchmark/config_utils.py
sdgym/_benchmark/credentials_utils.py
sdgym/cli/__init__.py
sdgym/cli/__main__.py
sdgym/cli/collect.py
sdgym/cli/summary.py
sdgym/cli/utils.py
sdgym/result_explorer/__init__.py
sdgym/result_explorer/result_explorer.py
sdgym/result_explorer/result_handler.py
sdgym/run_benchmark/__init__.py
sdgym/run_benchmark/run_benchmark.py
sdgym/run_benchmark/upload_benchmark_results.py
sdgym/run_benchmark/utils.py
sdgym/synthesizers/__init__.py
sdgym/synthesizers/base.py
sdgym/synthesizers/column.py
sdgym/synthesizers/generate.py
sdgym/synthesizers/identity.py
sdgym/synthesizers/realtabformer.py
sdgym/synthesizers/sdv.py
sdgym/synthesizers/uniform.py
sdgym/synthesizers/utils.py
sdgym-0.13.0.dist-info/licenses/LICENSE
sdgym-0.13.0.dist-info/METADATA
sdgym-0.13.0.dist-info/WHEEL
sdgym-0.13.0.dist-info/entry_points.txt
sdgym-0.13.0.dist-info/top_level.txt
sdgym-0.13.0.dist-info/RECORD
