Metadata-Version: 2.4
Name: sdgym
Version: 0.13.0
Summary: Benchmark tabular synthetic data generators using a variety of datasets
Author-email: "DataCebo, Inc." <info@sdv.dev>
License: BSL-1.1
Project-URL: Source Code, https://github.com/sdv-dev/SDGym/
Project-URL: Issue Tracker, https://github.com/sdv-dev/SDGym/issues
Project-URL: Changes, https://github.com/sdv-dev/SDGym/blob/main/HISTORY.md
Project-URL: Twitter, https://twitter.com/sdv_dev
Project-URL: Chat, https://bit.ly/sdv-slack-invite
Keywords: machine learning,synthetic data generation,benchmark,generative models
Classifier: Development Status :: 2 - Pre-Alpha
Classifier: Intended Audience :: Developers
Classifier: License :: Free for non-commercial use
Classifier: Natural Language :: English
Classifier: Programming Language :: Python :: 3
Classifier: Programming Language :: Python :: 3.9
Classifier: Programming Language :: Python :: 3.10
Classifier: Programming Language :: Python :: 3.11
Classifier: Programming Language :: Python :: 3.12
Classifier: Programming Language :: Python :: 3.13
Classifier: Topic :: Scientific/Engineering :: Artificial Intelligence
Requires-Python: <3.14,>=3.9
License-File: LICENSE
Requires-Dist: appdirs>=1.3
Requires-Dist: boto3<2,>=1.28
Requires-Dist: botocore<2,>=1.31
Requires-Dist: cloudpickle>=2.1.0
Requires-Dist: compress-pickle>=1.2.0
Requires-Dist: google-cloud-compute>=1.0.0
Requires-Dist: google-auth>=2.0.0
Requires-Dist: humanfriendly>=10.0
Requires-Dist: numpy>=1.22.2; python_version < "3.10"
Requires-Dist: numpy>=1.24.0; python_version >= "3.10" and python_version < "3.12"
Requires-Dist: numpy>=1.26.0; python_version >= "3.12" and python_version < "3.13"
Requires-Dist: numpy>=2.1.0; python_version >= "3.13"
Requires-Dist: openpyxl>=3.1.2
Requires-Dist: pandas<3.0.0,>=1.4.0; python_version < "3.11"
Requires-Dist: pandas<3.0.0,>=1.5.0; python_version >= "3.11" and python_version < "3.12"
Requires-Dist: pandas<3.0.0,>=2.1.1; python_version >= "3.12" and python_version < "3.13"
Requires-Dist: pandas<3.0.0,>=2.2.3; python_version >= "3.13"
Requires-Dist: psutil>=5.7
Requires-Dist: scikit-learn>=1.0.2; python_version < "3.10"
Requires-Dist: scikit-learn>=1.1.0; python_version >= "3.10" and python_version < "3.11"
Requires-Dist: scikit-learn>=1.1.3; python_version >= "3.11" and python_version < "3.12"
Requires-Dist: scikit-learn>=1.3.1; python_version >= "3.12" and python_version < "3.13"
Requires-Dist: scikit-learn>=1.5.2; python_version >= "3.13"
Requires-Dist: scipy>=1.7.3; python_version < "3.10"
Requires-Dist: scipy>=1.9.2; python_version >= "3.10" and python_version < "3.12"
Requires-Dist: scipy>=1.12.0; python_version >= "3.12" and python_version < "3.13"
Requires-Dist: scipy>=1.14.1; python_version >= "3.13"
Requires-Dist: tabulate<0.9,>=0.8.3
Requires-Dist: torch>=2.6.0
Requires-Dist: tqdm>=4.66.3
Requires-Dist: XlsxWriter>=1.2.8
Requires-Dist: rdt>=1.17.0
Requires-Dist: sdmetrics>=0.20.1
Requires-Dist: sdv>=1.21.0
Provides-Extra: dask
Requires-Dist: dask; extra == "dask"
Requires-Dist: distributed; extra == "dask"
Provides-Extra: realtabformer
Requires-Dist: realtabformer!=0.2.4,>=0.2.3; extra == "realtabformer"
Requires-Dist: torch>=2.6.0; extra == "realtabformer"
Requires-Dist: transformers<4.51; extra == "realtabformer"
Provides-Extra: test
Requires-Dist: sdgym[realtabformer]; extra == "test"
Requires-Dist: pytest>=6.2.5; extra == "test"
Requires-Dist: pytest-cov>=2.6.0; extra == "test"
Requires-Dist: jupyter<2,>=1.0.0; extra == "test"
Requires-Dist: tomli<3,>=2.0.0; extra == "test"
Requires-Dist: slack-sdk<4.0,>=3.23; extra == "test"
Requires-Dist: pydrive2<2.0.0,>=1.4.0; extra == "test"
Provides-Extra: dev
Requires-Dist: sdgym[dask,test]; extra == "dev"
Requires-Dist: build<2,>=1.0.0; extra == "dev"
Requires-Dist: bump-my-version>=0.18.3; extra == "dev"
Requires-Dist: pip>=9.0.1; extra == "dev"
Requires-Dist: watchdog<5,>=1.0.1; extra == "dev"
Requires-Dist: ruff<1,>=0.4.5; extra == "dev"
Requires-Dist: twine>=1.10.0; extra == "dev"
Requires-Dist: wheel>=0.30.0; extra == "dev"
Requires-Dist: coverage<8,>=4.5.12; extra == "dev"
Requires-Dist: importlib-metadata>=3.6; extra == "dev"
Requires-Dist: invoke; extra == "dev"
Provides-Extra: readme
Requires-Dist: rundoc<0.5,>=0.4.3; extra == "readme"
Provides-Extra: all
Requires-Dist: sdgym[dask,dev,test]; extra == "all"
Dynamic: license-file
